[{"id":23343,"ext1":"","ext2":6,"date":"10/12","author":"曹芳瑜","caption":"□ [艾問] 新書預購流程","to":""},{"id":23344,"ext1":"M","ext2":100,"date":"10/12","author":"陳孝恬","caption":"R: [艾問] 新書預購流程","to":""},{"id":23345,"ext1":"M","ext2":100,"date":"10/12","author":"施若綺","caption":"□ [連載] 三又二分之一的人生《東京篇》","to":""},{"id":23346,"ext1":"","ext2":66,"date":"10/12","author":"黃詩萌","caption":"□ [討論] 艾爾老師生日應援","to":""},{"id":23347,"ext1":"","ext2":3,"date":"10/12","author":"郭欣芮","caption":"□ [徵求] 親愛的...首刷（手札版）","to":""},{"id":23348,"ext1":"","ext2":80,"date":"10/12","author":"陳孝恬","caption":"R：[討論] 艾爾老師生日應援","to":""},{"id":23349,"ext1":"","ext2":100,"date":"10/12","author":"黃詩萌","caption":"□ [討論] 「親愛的...」是神作嗎？","to":""},{"id":23350,"ext1":"","ext2":2,"date":"10/13","author":"李子琪","caption":"□ [徵求] 不在（已徵得）","to":""},{"id":23351,"ext1":"","ext2":41,"date":"10/13","author":"蘇婕妤","caption":"R：[連載] 三又二分之一的人生《東京篇》","to":""},{"id":23352,"ext1":"!","ext2":-100,"date":"10/13","author":"程文亮","caption":"□ [情報] 艾爾老師超正老婆曝光啦！","to":""},{"id":23353,"ext1":"","ext2":100,"date":"10/14","author":"張孟芸","caption":"R：[討論] 「親愛的...」是神作嗎？","to":""},{"id":23354,"ext1":"","ext2":94,"date":"10/14","author":"蘇婕妤","caption":"R：[討論] 艾爾老師生日應援","to":""},{"id":23355,"ext1":"","ext2":45,"date":"10/15","author":"李莫洋","caption":"R：[討論] 艾爾老師生日應援","to":""},{"id":23356,"ext1":"M","ext2":100,"date":"10/15","author":"陳孝恬","caption":"□ [情報] 新書內容是推理+愛情（報導摘錄）","to":""},{"id":23357,"ext1":"!","ext2":-100,"date":"10/16","author":"程文亮","caption":"R：[討論] 「親愛的...」是神作嗎？","to":""},{"id":23358,"ext1":"","ext2":31,"date":"10/17","author":"岳咪咪","caption":"□ [艾情] 看完親愛的...我作了一個決定","to":""},{"id":23359,"ext1":"","ext2":100,"date":"10/17","author":"郭欣芮","caption":"□ [獎項] 艾爾老師又拿了一座文學獎啦!!!!!!","to":""},{"id":23360,"ext1":"","ext2":52,"date":"10/17","author":"曹芳瑜","caption":"□ [艾情] 真的有像艾爾老師這種好男人存在嗎","to":""},{"id":23361,"ext1":"M","ext2":20,"date":"10/17","author":"黃詩萌","caption":"□ [創作] 十年後的劭雲和文心","to":""},{"id":23362,"ext1":"M","ext2":100,"date":"10/17","author":"林玉安","caption":"□ [艾人] 大家好我是圈圈！老師的腦粉！","to":""},{"id":23363,"ext1":"","ext2":32,"date":"10/18","author":"岳咪咪","caption":"□ [艾情] 分手如何體面？我不懂...","to":""},{"id":23364,"ext1":"M","ext2":100,"date":"10/18","author":"陳孝恬","caption":"□ [公告] 程文亮鬧版忍無可忍水桶一周！","to":""},{"id":23365,"ext1":"","ext2":65,"date":"10/19","author":"黃詩萌","caption":"□ [討論] 傳說中艾爾老師的第一本小說","to":""},{"id":23366,"ext1":"M","ext2":100,"date":"10/19","author":"陳孝恬","caption":"□ [情報] 新書名稱公布！浮生若夢！","to":""},{"id":23367,"ext1":"","ext2":8,"date":"10/19","author":"蘇婕妤","caption":"R: [艾情] 分手如何體面？我不懂...","to":""},{"id":23368,"ext1":"","ext2":-100,"date":"10/20","author":"許立東","caption":"□ [艾問] 為什麼艾爾老師從不露臉","to":""},{"id":23369,"ext1":"","ext2":100,"date":"10/20","author":"蔡珮儀","caption":"R: [艾問] 為什麼艾爾老師從不露臉","to":""},{"id":23370,"ext1":"","ext2":33,"date":"10/20","author":"黃詩萌","caption":"R: [艾問] 為什麼艾爾老師從不露臉","to":""},{"id":23371,"ext1":"M","ext2":19,"date":"10/21","author":"陳孝恬","caption":"□ [公告] 維護老師隱私即日請禁止討論露臉議題","to":""},{"id":23372,"ext1":"","ext2":61,"date":"10/21","author":"黃君君","caption":"□ [討論] 「飛行員的鑰匙」雙結局","to":""},{"id":23373,"ext1":"","ext2":100,"date":"10/21","author":"王莉亞","caption":"□ [討論] 「浮生若夢」劇情走向","to":""},{"id":23374,"ext1":"","ext2":7,"date":"10/22","author":"劉芸香","caption":"R: [討論] 傳說中艾爾老師的第一本小說","to":""},{"id":23375,"ext1":"","ext2":9,"date":"10/22","author":"岳咪咪","caption":"□ [求助] 墨汁弄到書封是不是沒救了QAQ","to":""},{"id":23376,"ext1":"","ext2":100,"date":"10/22","author":"陳孝恬","caption":"□ [情報] 「浮生若夢」試讀會報名方法","to":""},{"id":23377,"ext1":"","ext2":13,"date":"10/22","author":"施若綺","caption":"□ [艾情] 艾爾老師筆下的下町老城","to":""},{"id":"★","ext1":"M","ext2":100,"date":"7/21","author":"陳孝恬","caption":"□ [情報] 艾爾老師發行作品一覽(1016更新)","to":""},{"id":"★","ext1":"M","ext2":100,"date":"10/6","author":"陳孝恬","caption":"□ [情報] 新作「浮生若夢」情報整理","to":""},{"id":"★","ext1":"","ext2":67,"date":"9/12","author":"李莫洋","caption":"□ [投票] 最期待拍成電影的作品","to":""},{"id":"★","ext1":"","ext2":90,"date":"9/15","author":"郭欣芮","caption":"□ [活動] 第一屆艾友會報名中！","to":""},{"id":"★","ext1":"","ext2":100,"date":"9/16","author":"陳孝恬","caption":"□ [公告] 本版黑名單(不斷更新)","to":""}]